stash/__init__.py
stash/main.py
stash/cache/__init__.py
stash/cache/cache_registry.py
stash/classes/__init__.py
stash/classes/fieldinfo.py
stash/classes/slots_class.py
stash/errors/__init__.py
stash/errors/exceptions.py
stash/utils/__init__.py
stash/utils/dynamic.py
stash/utils/utility.py
stash_memory-0.0.1.dist-info/licenses/LICENSE
stash_memory-0.0.1.dist-info/METADATA
stash_memory-0.0.1.dist-info/WHEEL
stash_memory-0.0.1.dist-info/top_level.txt
stash_memory-0.0.1.dist-info/RECORD
