Metadata-Version: 2.4
Name: stash-memory
Version: 0.0.1
Summary: A memory optimization tool designed to lessen Python class overhead
Author-email: HysingerDev <HysingerDev@gmail.com>
License: MIT License
Project-URL: Homepage, https://github.com/MassivelyOverthinking/Stash
Project-URL: Documentation, https://github.com/MassivelyOverthinking/Stash
Project-URL: Source, https://github.com/MassivelyOverthinking/Stash
Project-URL: Issues, https://github.com/MassivelyOverthinking/Stash
Keywords: slots,memory optimization,performance,monitoring,python,decorator,class,freeze,immutability,interning,lightweight classes
Classifier: Development Status :: 3 - Alpha
Classifier: Intended Audience :: Developers
Classifier: License :: OSI Approved :: MIT License
Classifier: Operating System :: OS Independent
Classifier: Programming Language :: Python
Classifier: Programming Language :: Python :: 3
Classifier: Programming Language :: Python :: 3.8
Classifier: Programming Language :: Python :: 3.9
Classifier: Programming Language :: Python :: 3.10
Classifier: Programming Language :: Python :: 3.11
Classifier: Programming Language :: Python :: 3.12
Classifier: Topic :: Software Development :: Libraries
Classifier: Topic :: Utilities
Requires-Python: >=3.8
License-File: LICENSE
Provides-Extra: dev
Requires-Dist: pytest>=8.4.1; extra == "dev"
Requires-Dist: pympler>=1.1; extra == "dev"
Requires-Dist: iniconfig>=2.1.0; extra == "dev"
Requires-Dist: pluggy>=1.6.0; extra == "dev"
Requires-Dist: packaging>=25.0; extra == "dev"
Requires-Dist: Pygments>=2.19.2; extra == "dev"
Dynamic: license-file
